{
    "ProjectName": "Heat 1d 1node", 
    "Solver": {
        "SolverIdx": 0, 
        "StartTime": 0.0, 
        "FinishTime": 0.1, 
        "TimeStep": 1e-07, 
        "SaveInterval": 0.0, 
        "AbsTolerance": 0.001, 
        "RelTolerance": 0.001
    }, 
    "Grid": {
        "Dimension": 1, 
        "dx": 0.001, 
        "dy": 1, 
        "dz": 1
    }, 
    "Blocks": [
        {
            "Name": "Block#0", 
            "Offset": {
                "x": 0.0
            }, 
            "Size": {
                "x": 1.0
            }, 
            "DefaultEquation": 0, 
            "DefaultInitial": 0, 
            "BoundRegions": [], 
            "InitialRegions": [
                {
                    "InitialNumber": 1, 
                    "xfrom": 0.25, 
                    "xto": 0.75
                }
            ], 
            "EquationRegions": []
        }
    ], 
    "Interconnects": [], 
    "Equations": [
        {
            "Name": "Flat Brusselator", 
            "Vars": [
                "x"
            ], 
            "System": [
                "U'=a * D[U,{x,2}]"
            ]
        }
    ], 
    "EquationParams": {
        "Params": [
            "a"
        ], 
        "ParamValues": [
            {
                "a": 1.0
            }
        ], 
        "DefaultParamsIndex": 0
    }, 
    "Bounds": [], 
    "Initials": [
        {
            "Name": "Initial values 0", 
            "Values": [
                "0.0"
            ]
        }, 
        {
            "Name": "Initial values 1", 
            "Values": [
                "1.0"
            ]
        }
    ], 
    "Hardware": [
        {
            "Name": "cnode1", 
            "CpuCount": 1, 
            "GpuCount": 3
        }
    ], 
    "Mapping": {
        "IsMapped": true, 
        "BlockMapping": [
            {
                "NodeIdx": 0, 
                "DeviceType": "cpu", 
                "DeviceIdx": 0
            }
        ]
    }, 
    "Plots": []
}